mbed_lstools/__init__.py
mbed_lstools/darwin.py
mbed_lstools/linux.py
mbed_lstools/lstools_base.py
mbed_lstools/main.py
mbed_lstools/platform_database.py
mbed_lstools/windows.py
test/__init__.py
test/base.py
test/details_txt.py
test/detect_os.py
test/mbed_htm.py
test/mbedls_toolsbase.py
test/os_darwin.py
test/os_linux_generic.py
test/os_win7.py
test/platform_database.py
test/platform_detection.py
mbed_ls-1.8.14.dist-info/METADATA
mbed_ls-1.8.14.dist-info/WHEEL
mbed_ls-1.8.14.dist-info/entry_points.txt
mbed_ls-1.8.14.dist-info/top_level.txt
mbed_ls-1.8.14.dist-info/RECORD
