Metadata-Version: 2.1
Name: mbed-ls
Version: 1.8.14
Summary: mbed-ls is a Python module that detects and lists mbed-enabled devices connected to the host computer
Home-page: https://github.com/ARMmbed/mbed-os-tools
Author: Graham Hammond, Mark Edgeworth
Author-email: Graham.Hammond@arm.com, Mark.Edgeworth@arm.com
Maintainer: Graham Hammond, Mark Edgeworth
Maintainer-email: Graham.Hammond@arm.com, Mark.Edgeworth@arm.com
License: Apache-2.0
Platform: UNKNOWN
Classifier: Development Status :: 5 - Production/Stable
Classifier: Intended Audience :: Developers
Classifier: License :: OSI Approved :: Apache Software License
Classifier: Programming Language :: Python :: 2
Classifier: Programming Language :: Python :: 2.7
Classifier: Programming Language :: Python :: 3
Classifier: Programming Language :: Python :: 3.5
Classifier: Programming Language :: Python :: 3.6
Classifier: Programming Language :: Python :: 3.7
Classifier: Programming Language :: Python
Classifier: Topic :: Software Development :: Build Tools
Classifier: Topic :: Software Development :: Embedded Systems
Requires-Python: >=2.7.10, !=3.0.*, !=3.1.*, !=3.2.*, !=3.3.*, !=3.4.*, <4
Requires-Dist: mbed-os-tools (>=0.0.9)
Requires-Dist: PrettyTable (<=1.0.1) ; python_version < "3.6"
Requires-Dist: prettytable (<3.0,>=2.0) ; python_version >= "3.6"
Provides-Extra: colorized_logs
Requires-Dist: colorlog ; extra == 'colorized_logs'
